COPYING
README
pyproject.toml
setup.cfg
setup.py
rbfly/__init__.py
rbfly/_buffer.c
rbfly/_buffer.pxd
rbfly/_buffer.pyx
rbfly/_codec.c
rbfly/_codec.h
rbfly/_codec.pxd
rbfly/_codec.pyx
rbfly/cm.py
rbfly/error.py
rbfly/py.typed
rbfly/slotmap.py
rbfly/types.py
rbfly/util.py
rbfly.egg-info/PKG-INFO
rbfly.egg-info/SOURCES.txt
rbfly.egg-info/dependency_links.txt
rbfly.egg-info/requires.txt
rbfly.egg-info/top_level.txt
rbfly/amqp/__init__.py
rbfly/amqp/_message.c
rbfly/amqp/_message.pxd
rbfly/amqp/_message.pyi
rbfly/amqp/_message.pyx
rbfly/streams/__init__.py
rbfly/streams/_client.c
rbfly/streams/_client.pyi
rbfly/streams/_client.pyx
rbfly/streams/_codec.c
rbfly/streams/_codec.pyi
rbfly/streams/_codec.pyx
rbfly/streams/_mqueue.c
rbfly/streams/_mqueue.pxd
rbfly/streams/_mqueue.pyi
rbfly/streams/_mqueue.pyx
rbfly/streams/client.py
rbfly/streams/codec.py
rbfly/streams/const.py
rbfly/streams/error.py
rbfly/streams/offset.py
rbfly/streams/protocol.py
rbfly/streams/types.py
rbfly/streams/util.py
rbfly/tests/__init__.py
rbfly/tests/test_slotmap.py
rbfly/tests/test_util.py
rbfly/tests/amqp/__init__.py
rbfly/tests/amqp/test_message.py
rbfly/tests/streams/__init__.py
rbfly/tests/streams/test_client.py
rbfly/tests/streams/test_codec.py
rbfly/tests/streams/test_mqueue.py
rbfly/tests/streams/test_offset.py