Metadata-Version: 2.4
Name: rbfly
Version: 0.11.0
Summary: RbFly - a library for RabbitMQ Streams using Python asyncio
Home-page: https://wrobell.dcmod.org/rbfly/
Author: Artur Wroblewski
Author-email: wrobell@riseup.net
License: GPL-3.0-or-later
Project-URL: Source Code, https://gitlab.com/wrobell/rbfly
Project-URL: Bug tracker, https://gitlab.com/wrobell/rbfly/issues
Classifier: Topic :: Software Development :: Libraries
Classifier: Programming Language :: Python :: 3
Classifier: Development Status :: 4 - Beta
Requires-Python: >=3.12
License-File: COPYING
Provides-Extra: tests
Requires-Dist: bandit; extra == "tests"
Requires-Dist: cython-lint; extra == "tests"
Requires-Dist: mypy==1.18.2; extra == "tests"
Requires-Dist: pika; extra == "tests"
Requires-Dist: pytest-asyncio; extra == "tests"
Requires-Dist: pytest-cov; extra == "tests"
Requires-Dist: pytest-lazy-fixtures; extra == "tests"
Requires-Dist: pytest-timeout; extra == "tests"
Requires-Dist: ruff>=0.12.9; extra == "tests"
Requires-Dist: uvloop>=0.21.0; extra == "tests"
Provides-Extra: performance
Requires-Dist: msgpack; extra == "performance"
Requires-Dist: aiokafka==0.12.0; extra == "performance"
Requires-Dist: rstream==0.40.0; extra == "performance"
Requires-Dist: python-qpid-proton==0.40.0; extra == "performance"
Provides-Extra: doc
Requires-Dist: sphinx_rtd_theme; extra == "doc"
Dynamic: license-file
